sdeux/__init__.py
sdeux/auto_detect.py
sdeux/base.py
sdeux/communication.py
sdeux/defs.py
sdeux/exceptions.py
sdeux/gen2005.py
sdeux/gen4.py
sdeux/gen5.py
sdeux/serial_handler.py
sdeux/synchronize.py
sdeux/examples/__init__.py
sdeux/examples/basic.py
sdeux/updater/__init__.py
sdeux/updater/raspi.py
sdeux/updater/writer.py
sdeux/utils/__init__.py
sdeux/utils/alparser.py
sdeux-1.2.7.dist-info/AUTHORS
sdeux-1.2.7.dist-info/LICENSE
sdeux-1.2.7.dist-info/METADATA
sdeux-1.2.7.dist-info/WHEEL
sdeux-1.2.7.dist-info/entry_points.txt
sdeux-1.2.7.dist-info/pbr.json
sdeux-1.2.7.dist-info/top_level.txt
sdeux-1.2.7.dist-info/RECORD
