Metadata-Version: 2.1
Name: sdeux
Version: 1.2.7
Summary: UNKNOWN
Home-page: UNKNOWN
Author: chiesa
Author-email: UNKNOWN
License: Proprietary
Keywords: sdeux
Platform: UNKNOWN
Classifier: Intended Audience :: Developers
Classifier: License :: Other/Proprietary License
Classifier: Natural Language :: English
Classifier: Programming Language :: Python :: 3
Requires-Dist: pyserial
